[
  {
    "name": "Will we skip our trip to the store?",
    "canonical": "!storeOpen || linesTooLong",
    "answer": "storeOpen == linesToolong",
    "correct": false,
    "timestamp": 1663883192079
  },
  {
    "name": "Will we skip our trip to the store?",
    "canonical": "!storeOpen || linesTooLong",
    "answer": "storeOpen == linesTooLong",
    "correct": false,
    "timestamp": 1663883196815
  },
  {
    "name": "Will we skip our trip to the store?",
    "canonical": "!storeOpen || linesTooLong",
    "answer": "storeOpen && linesTooLong",
    "correct": false,
    "timestamp": 1663883201566
  },
  {
    "name": "Will we skip our trip to the store?",
    "canonical": "!storeOpen || linesTooLong",
    "answer": "!storeOpen == linesTooLong",
    "correct": false,
    "timestamp": 1663884648754
  },
  {
    "name": "Will we skip our trip to the store?",
    "canonical": "!storeOpen || linesTooLong",
    "answer": "!storeOpen || linesTooLong",
    "correct": true,
    "timestamp": 1663884706459
  },
  {
    "name": "Wait for a sale?",
    "canonical": "!storeOpen || !isASale",
    "answer": "!storeOpen || isASale",
    "correct": false,
    "timestamp": 1663884746596
  },
  {
    "name": "Wait for a sale?",
    "canonical": "!storeOpen || !isASale",
    "answer": "!storeOpen || !isASale",
    "correct": true,
    "timestamp": 1663884754516
  },
  {
    "name": "Coming to bookclub?",
    "canonical": "member && !outSick",
    "answer": "member || !outSick",
    "correct": false,
    "timestamp": 1663884825550
  },
  {
    "name": "Coming to bookclub?",
    "canonical": "member && !outSick",
    "answer": "!member || !outSick",
    "correct": false,
    "timestamp": 1663884833470
  },
  {
    "name": "Coming to bookclub?",
    "canonical": "member && !outSick",
    "answer": "!member && !outSick",
    "correct": false,
    "timestamp": 1663884846847
  },
  {
    "name": "Coming to bookclub?",
    "canonical": "member && !outSick",
    "answer": "member && outSick",
    "correct": false,
    "timestamp": 1663884850215
  },
  {
    "name": "Coming to bookclub?",
    "canonical": "member && !outSick",
    "answer": "member || !outSick",
    "correct": false,
    "timestamp": 1663884893856
  },
  {
    "name": "Coming to bookclub?",
    "canonical": "member && !outSick",
    "answer": "member !== outSick",
    "correct": false,
    "timestamp": 1663884929145
  },
  {
    "name": "Coming to bookclub?",
    "canonical": "member && !outSick",
    "answer": "member && !outSick",
    "correct": true,
    "timestamp": 1663884967907
  },
  {
    "name": "Ready for some football?",
    "canonical": "fast && strong",
    "answer": "fast == strong",
    "correct": false,
    "timestamp": 1663884988115
  },
  {
    "name": "Ready for some football?",
    "canonical": "fast && strong",
    "answer": "fast || strong",
    "correct": false,
    "timestamp": 1663884997155
  },
  {
    "name": "Ready for some football?",
    "canonical": "fast && strong",
    "answer": "fast || !strong",
    "correct": false,
    "timestamp": 1663885035404
  },
  {
    "name": "Ready for some football?",
    "canonical": "fast && strong",
    "answer": "!fast || strong",
    "correct": false,
    "timestamp": 1663885040748
  },
  {
    "name": "Ready for some football?",
    "canonical": "fast && strong",
    "answer": "fast && strong",
    "correct": true,
    "timestamp": 1663885132319
  },
  {
    "name": "Lighting a fire?",
    "canonical": "fireLit || !haveMatches",
    "answer": "FireLit && !haveMatches",
    "correct": false,
    "timestamp": 1663885247634
  },
  {
    "name": "Lighting a fire?",
    "canonical": "fireLit || !haveMatches",
    "answer": "fireLit && haveMatches",
    "correct": false,
    "timestamp": 1663885253763
  },
  {
    "name": "Lighting a fire?",
    "canonical": "fireLit || !haveMatches",
    "answer": "fireLit && !haveMatches",
    "correct": false,
    "timestamp": 1663885258203
  },
  {
    "name": "Lighting a fire?",
    "canonical": "fireLit || !haveMatches",
    "answer": "!fireLit && haveMatches",
    "correct": false,
    "timestamp": 1663885261779
  },
  {
    "name": "Lighting a fire?",
    "canonical": "fireLit || !haveMatches",
    "answer": "!fireLit === haveMatches",
    "correct": false,
    "timestamp": 1663885277688
  },
  {
    "name": "Lighting a fire?",
    "canonical": "fireLit || !haveMatches",
    "answer": "!fireLit && haveMatches",
    "correct": false,
    "timestamp": 1664229229403
  },
  {
    "name": "Lighting a fire?",
    "canonical": "fireLit || !haveMatches",
    "answer": "fireLit && haveMatches",
    "correct": false,
    "timestamp": 1664229232706
  },
  {
    "name": "Lighting a fire?",
    "canonical": "fireLit || !haveMatches",
    "answer": "fireLit !== haveMatches",
    "correct": false,
    "timestamp": 1664229240962
  },
  {
    "name": "Lighting a fire?",
    "canonical": "fireLit || !haveMatches",
    "answer": "!fireLit && !haveMatches",
    "correct": false,
    "timestamp": 1664229253947
  },
  {
    "name": "Lighting a fire?",
    "canonical": "fireLit || !haveMatches",
    "answer": "fireLit && !haveMatches",
    "correct": false,
    "timestamp": 1664229257003
  },
  {
    "name": "Lighting a fire?",
    "canonical": "fireLit || !haveMatches",
    "answer": "fireLit || haveMatches",
    "correct": false,
    "timestamp": 1664229787641
  },
  {
    "name": "Lighting a fire?",
    "canonical": "fireLit || !haveMatches",
    "answer": "fireLit || !haveMatches",
    "correct": true,
    "timestamp": 1664229788952
  },
  {
    "name": "Can pay attention?",
    "canonical": "!hungry && interested",
    "answer": "hungry || !intrested",
    "correct": false,
    "timestamp": 1664229819705
  },
  {
    "name": "Can pay attention?",
    "canonical": "!hungry && interested",
    "answer": "hungry || !interested",
    "correct": false,
    "timestamp": 1664229828425
  },
  {
    "name": "Can pay attention?",
    "canonical": "!hungry && interested",
    "answer": "hungry || interested",
    "correct": false,
    "timestamp": 1664229832802
  },
  {
    "name": "Can pay attention?",
    "canonical": "!hungry && interested",
    "answer": "hungry && interested",
    "correct": false,
    "timestamp": 1664229838890
  },
  {
    "name": "Can pay attention?",
    "canonical": "!hungry && interested",
    "answer": "hungry && !interested",
    "correct": false,
    "timestamp": 1664229841290
  },
  {
    "name": "Can pay attention?",
    "canonical": "!hungry && interested",
    "answer": "hungry == !interested",
    "correct": false,
    "timestamp": 1664229846850
  },
  {
    "name": "Can pay attention?",
    "canonical": "!hungry && interested",
    "answer": "hungry || interested",
    "correct": false,
    "timestamp": 1664402725610
  },
  {
    "name": "Can pay attention?",
    "canonical": "!hungry && interested",
    "answer": "hungry || !interested",
    "correct": false,
    "timestamp": 1664402817725
  }
]